pyotp_cli/__init__.py
pyotp_cli/cli_hotp.py
pyotp_cli/utils.py
pyotp_cli-0.1.2.dist-info/METADATA
pyotp_cli-0.1.2.dist-info/WHEEL
pyotp_cli-0.1.2.dist-info/entry_points.txt
pyotp_cli-0.1.2.dist-info/RECORD
