Metadata-Version: 2.1
Name: pyotp-cli
Version: 0.1.2
Summary: Convenient CLIs for pyotp, supports TOTP & HTOP
Home-page: https://github.com/tddschn/pyotp-cli
License: MIT
Keywords: OTP,2FA,TOTP,HOTP,CLI,pyotp
Author: Teddy Xinyuan Chen
Author-email: 45612704+tddschn@users.noreply.github.com
Requires-Python: >=3.12,<4.0
Classifier: License :: OSI Approved :: MIT License
Classifier: Programming Language :: Python :: 3
Classifier: Programming Language :: Python :: 3.12
Classifier: Topic :: Utilities
Requires-Dist: pyotp (>=2.9.0,<3.0.0)
Project-URL: Bug Tracker, https://github.com/tddschn/pyotp-cli/issues
Project-URL: Repository, https://github.com/tddschn/pyotp-cli
